{
  "project_info": {
    "project_number": "12384404765",
    "project_id": "tinder-af728",
    "storage_bucket": "tinder-af728.appspot.com"
  },
  "client": [
    {
      "client_info": {
        "mobilesdk_app_id": "1:12384404765:android:21128f6e7c33e5eeeecdf4",
        "android_client_info": {
          "package_name": "com.tinder"
        }
      },
      "oauth_client": [
        {
          "client_id": "12384404765-44t2opis1um3imshe6u8n09hnb30tpgg.apps.googleusercontent.com",
          "client_type": 3
        }
      ],
      "api_key": [
        {
          "current_key": "AIzaSyCFQ90dEVIgvXYC9PowiA5vxfuR703G_dY"
        }
      ],
      "services": {
        "appinvite_service": {
          "other_platform_oauth_client": [
            {
              "client_id": "12384404765-44t2opis1um3imshe6u8n09hnb30tpgg.apps.googleusercontent.com",
              "client_type": 3
            }
          ]
        }
      }
    }
  ],
  "configuration_version": "1"
}